{
  "data_summary": "Owl wing feathers reduce flight noise by breaking up airflow. Caption: STEALTH AIRFRAME",
  "expires_at": "2026-07-17T22:20:36+10:00",
  "kind": "fact",
  "label": "OPEN FACT",
  "lane": "local_signal",
  "published_at": "2026-07-17T16:20:36+10:00",
  "title": "Curious Fact: OWLS FLY WITH SOUND-DAMPING FEATHERS",
  "topic_key": "curious_fact_owl_silent_feathers",
  "url": "https://www.google.com/search?q=Owl+wing+feathers+reduce+flight+noise+by+breaking+up+airflow.+Caption%3A+STEALTH+AIRFRAME"
}
